{"cameraMode":{"drawMode":0,"name":"Shaded","section":"Shading Mode"},"sceneLighting":true,"audioPlay":false,"sceneViewState":{"showFog":true,"showMaterialUpdate":false,"showSkybox":true,"showFlares":true,"showImageEffects":true,"showParticleSystems":true},"in2DMode":false,"pivot":{"x":2.745762348175049,"y":3.54329514503479,"z":-1.6741567850112916},"rotation":{"x":-0.07903121411800385,"y":0.9127394556999207,"z":-0.2120850384235382,"w":-0.34012195467948916},"size":2.9700000286102297,"orthographic":false}