{"cameraMode":{"drawMode":0,"name":"Shaded","section":"Shading Mode"},"sceneLighting":true,"audioPlay":false,"sceneViewState":{"showFog":true,"showMaterialUpdate":false,"showSkybox":true,"showFlares":true,"showImageEffects":true,"showParticleSystems":true},"in2DMode":false,"pivot":{"x":3.6413629055023195,"y":3.054191827774048,"z":-2.263157844543457},"rotation":{"x":-0.13919483125209809,"y":0.8448083996772766,"z":-0.44337642192840578,"w":-0.2652216851711273},"size":2.9700000286102297,"orthographic":false}